odoo/addons/stock_weighing_auto_package/README.rst
odoo/addons/stock_weighing_auto_package/__init__.py
odoo/addons/stock_weighing_auto_package/__manifest__.py
odoo/addons/stock_weighing_auto_package/i18n/nl.po
odoo/addons/stock_weighing_auto_package/i18n/nl_NL.po
odoo/addons/stock_weighing_auto_package/i18n/stock_weighing_auto_package.pot
odoo/addons/stock_weighing_auto_package/models/__init__.py
odoo/addons/stock_weighing_auto_package/models/product.py
odoo/addons/stock_weighing_auto_package/readme/CONTRIBUTORS.rst
odoo/addons/stock_weighing_auto_package/readme/DESCRIPTION.rst
odoo/addons/stock_weighing_auto_package/static/description/icon.png
odoo/addons/stock_weighing_auto_package/static/description/index.html
odoo/addons/stock_weighing_auto_package/wizards/__init__.py
odoo/addons/stock_weighing_auto_package/wizards/weighing_wizard.py
odoo/addons/stock_weighing_auto_package/wizards/weighing_wizard_views.xml
odoo_addon_stock_weighing_auto_package-15.0.1.1.0.3.dist-info/METADATA
odoo_addon_stock_weighing_auto_package-15.0.1.1.0.3.dist-info/WHEEL
odoo_addon_stock_weighing_auto_package-15.0.1.1.0.3.dist-info/top_level.txt
odoo_addon_stock_weighing_auto_package-15.0.1.1.0.3.dist-info/RECORD
